ChangeLog
MANIFEST.in
README.md
setup.py
Safeout.egg-info/PKG-INFO
Safeout.egg-info/SOURCES.txt
Safeout.egg-info/dependency_links.txt
Safeout.egg-info/top_level.txt
safeout/__init__.py
safeout/safeout.py
safeout/safeout_version.py