Metadata-Version: 1.1
Name: Safeout
Version: 0.2.1
Summary: Write out a file safely (atomically)
Home-page: UNKNOWN
Author: Luis Pedro Coelho
Author-email: luis@luispedro.org
License: MIT
Platform: Any
Classifier: License :: OSI Approved :: MIT License
Classifier: Operating System :: POSIX
Classifier: Operating System :: OS Independent
Classifier: Programming Language :: Python
